c0mplh4cks/__init__.py
c0mplh4cks/packnet/ARP.py
c0mplh4cks/packnet/DNS.py
c0mplh4cks/packnet/ETHERNET.py
c0mplh4cks/packnet/ICMP.py
c0mplh4cks/packnet/ICMPv6.py
c0mplh4cks/packnet/IPv4.py
c0mplh4cks/packnet/IPv6.py
c0mplh4cks/packnet/MQTT.py
c0mplh4cks/packnet/TCP.py
c0mplh4cks/packnet/UDP.py
c0mplh4cks/packnet/__init__.py
c0mplh4cks/packnet/interface.py
c0mplh4cks/packnet/packnet.py
c0mplh4cks/packnet/standards.py
c0mplh4cks/packnet/vendor.py
c0mplh4cks/screem/__init__.py
c0mplh4cks/screem/screem.py
c0mplh4cks_pylib-1.6.1.dist-info/LICENSE
c0mplh4cks_pylib-1.6.1.dist-info/METADATA
c0mplh4cks_pylib-1.6.1.dist-info/WHEEL
c0mplh4cks_pylib-1.6.1.dist-info/top_level.txt
c0mplh4cks_pylib-1.6.1.dist-info/RECORD
