Metadata-Version: 2.1
Name: c0mplh4cks-pylib
Version: 1.6.1
Summary: c0mplh4cks's custom library's including Screem and Packnet
Home-page: https://github.com/c0mplh4cks/python3-library
Author: c0mplh4cks
License: MIT
Platform: UNKNOWN
Requires-Python: >=3
